pyaxmlparser/__init__.py
pyaxmlparser/arscparser.py
pyaxmlparser/arscutil.py
pyaxmlparser/axmlparser.py
pyaxmlparser/axmlprinter.py
pyaxmlparser/bytecode.py
pyaxmlparser/cli.py
pyaxmlparser/constants.py
pyaxmlparser/core.py
pyaxmlparser/stringblock.py
pyaxmlparser/utils.py
pyaxmlparser/resources/__init__.py
pyaxmlparser/resources/public.json
pyaxmlparser/resources/public.py
pyaxmlparser/resources/public.xml
pyaxmlparser-0.3.31.data/data/share/man/man1/apkinfo.1
pyaxmlparser-0.3.31.dist-info/LICENSE
pyaxmlparser-0.3.31.dist-info/METADATA
pyaxmlparser-0.3.31.dist-info/WHEEL
pyaxmlparser-0.3.31.dist-info/entry_points.txt
pyaxmlparser-0.3.31.dist-info/top_level.txt
pyaxmlparser-0.3.31.dist-info/RECORD
