Metadata-Version: 2.1
Name: pyaxmlparser
Version: 0.3.31
Summary: Python3 Parser for Android XML file and get Application Name without using Androguard
Home-page: https://github.com/appknox/pyaxmlparser
Author: Subho Halder
Author-email: sunny@appknox.com
License: Apache License 2.0
Keywords: appknox axmlparser arscparser android
Platform: any
Classifier: Development Status :: 4 - Beta
Classifier: Intended Audience :: Developers
Classifier: License :: OSI Approved :: Apache Software License
Classifier: Operating System :: POSIX
Classifier: Operating System :: MacOS
Classifier: Operating System :: Unix
Classifier: Programming Language :: Python
Classifier: Programming Language :: Python :: 3
Classifier: Programming Language :: Python :: 3.5
Classifier: Topic :: Software Development :: Build Tools
Classifier: Topic :: Software Development :: Libraries :: Python Modules
License-File: LICENSE
Requires-Dist: lxml
Requires-Dist: click>=6.7
Requires-Dist: asn1crypto>=0.24.0
